g2pk3/__init__.py
g2pk3/english.py
g2pk3/g2pk3.py
g2pk3/idioms.txt
g2pk3/japanese.py
g2pk3/korean.py
g2pk3/numerals.py
g2pk3/regular.py
g2pk3/rules.txt
g2pk3/special.py
g2pk3/table.csv
g2pk3/utils.py
g2pk3-1.4.dist-info/LICENSE
g2pk3-1.4.dist-info/METADATA
g2pk3-1.4.dist-info/WHEEL
g2pk3-1.4.dist-info/dependency_links.txt
g2pk3-1.4.dist-info/top_level.txt
g2pk3-1.4.dist-info/RECORD
