Metadata-Version: 2.1
Name: g2pk3
Version: 1.4
Home-page: https://github.com/kdrkdrkdr/g2pk3
Author: kdr
Author-email: kdrhacker1234@gmail.com
License: MIT
Classifier: Programming Language :: Python :: 3
Classifier: Programming Language :: Python :: 3.7
Classifier: Programming Language :: Python :: 3.8
Classifier: Programming Language :: Python :: 3.9
Classifier: Programming Language :: Python :: 3.10
Classifier: License :: OSI Approved :: MIT License
Classifier: Operating System :: OS Independent
License-File: LICENSE
Requires-Dist: jamo
Requires-Dist: g2p-en
